accel_brain_base-1.0.1.dist-info/METADATA
accel_brain_base-1.0.1.dist-info/RECORD
accel_brain_base-1.0.1.dist-info/WHEEL
accel_brain_base-1.0.1.dist-info/top_level.txt
accelbrainbase/__init__.py
accelbrainbase/computable_loss.py
accelbrainbase/controllable_model.py
accelbrainbase/extractable_data.py
accelbrainbase/iteratable_data.py
accelbrainbase/noiseable_data.py
accelbrainbase/observable_data.py
accelbrainbase/regularizatable_data.py
accelbrainbase/samplable_data.py
accelbrainbase/_mxnet/__init__.py
accelbrainbase/_mxnet/global_avg_pool_2d.py
accelbrainbase/_mxnet/initializable_params.py
accelbrainbase/_mxnet/relu_n.py
accelbrainbase/_mxnet/_exception/__init__.py
accelbrainbase/_mxnet/_exception/init_deferred_error.py
accelbrainbase/_mxnet/initializableparams/__init__.py
accelbrainbase/_mxnet/initializableparams/normal_initializer.py
accelbrainbase/computableloss/__init__.py
accelbrainbase/computableloss/_mxnet/__init__.py
accelbrainbase/computableloss/_mxnet/discriminator_loss.py
accelbrainbase/computableloss/_mxnet/drcn_loss.py
accelbrainbase/computableloss/_mxnet/generator_loss.py
accelbrainbase/computableloss/_mxnet/l2_norm_loss.py
accelbrainbase/computableloss/_mxnet/discriminatorloss/__init__.py
accelbrainbase/computableloss/_mxnet/discriminatorloss/eb_discriminator_loss.py
accelbrainbase/controllablemodel/__init__.py
accelbrainbase/controllablemodel/_mxnet/__init__.py
accelbrainbase/controllablemodel/_mxnet/dql_controller.py
accelbrainbase/controllablemodel/_mxnet/gan_controller.py
accelbrainbase/controllablemodel/_mxnet/dqlcontroller/__init__.py
accelbrainbase/controllablemodel/_mxnet/dqlcontroller/dqn_controller.py
accelbrainbase/controllablemodel/_mxnet/gancontroller/__init__.py
accelbrainbase/controllablemodel/_mxnet/gancontroller/aae_controller.py
accelbrainbase/controllablemodel/_mxnet/gancontroller/ebgan_controller.py
accelbrainbase/controllablemodel/_mxnet/gancontroller/aaecontroller/__init__.py
accelbrainbase/controllablemodel/_mxnet/gancontroller/aaecontroller/ebaae_controller.py
accelbrainbase/extractabledata/__init__.py
accelbrainbase/extractabledata/image_extractor.py
