Metadata-Version: 2.1
Name: accel-brain-base
Version: 1.0.1
Summary: accel-brain-base is a basic library of the Deep Learning for rapid development at low cost. This library makes it possible to design and implement deep learning, which must be configured as a complex system, by combining a plurality of functionally differentiated modules such as a Restricted Boltzmann Machine(RBM), Deep Boltzmann Machines(DBMs), a Stacked-Auto-Encoder, an Encoder/Decoder based on Long Short-Term Memory(LSTM), and a Convolutional Auto-Encoder(CAE).
Home-page: https://github.com/accel-brain/accel-brain-code/tree/master/Accel-Brain-Base/
Author: accel-brain
Author-email: info@accel-brain.co.jp
License: GPL2
Keywords: Generative Adversarial Networks Adversarial Auto-Encoders autoencoder auto-encoder convolution deconvolution encoder decoder LSTM Deep Q-Learning Deep Reinforcement Learning Deep Boltzmann Machines Restricted Boltzmann Machine Ladder Networks semi-supervised learning DRCN
Platform: UNKNOWN
Classifier: Development Status :: 5 - Production/Stable
Classifier: Intended Audience :: Information Technology
Classifier: Intended Audience :: Science/Research
Classifier: Framework :: Robot Framework
Classifier: Topic :: Text Processing
Classifier: Topic :: Scientific/Engineering :: Artificial Intelligence
Classifier: License :: OSI Approved :: GNU General Public License v2 (GPLv2)
Classifier: Programming Language :: Python :: 3
Requires-Dist: numpy
Requires-Dist: pandas
